py_template_expander/__init__.py
py_template_expander-2025.9.131516.dist-info/licenses/LICENSE
py_template_expander-2025.9.131516.dist-info/METADATA
py_template_expander-2025.9.131516.dist-info/WHEEL
py_template_expander-2025.9.131516.dist-info/top_level.txt
py_template_expander-2025.9.131516.dist-info/RECORD
